{
  "barcode_scanner.png": "images/barcode_scanner.png",
  "card_reader.png": "images/card_reader.png",
  "sample_credit_card.jpg": "images/sample_credit_card.jpg",
  "갈비탕.png": "images/갈비탕.png",
  "김치찌개.png": "images/김치찌개.png",
  "낙지덮밥.jpg": "images/낙지덮밥.jpg",
  "된장찌개.jpg": "images/된장찌개.jpg",
  "불고기정식.png": "images/불고기정식.png",
  "비빔밥.jpg": "images/비빔밥.jpg",
  "사이다.png": "images/사이다.png",
  "소머리국밥.png": "images/소머리국밥.png",
  "순대국밥.png": "images/순대국밥.png",
  "순두부찌개.jpg": "images/순두부찌개.jpg",
  "제로사이다.png": "images/제로사이다.png",
  "제로콜라.png": "images/제로콜라.png",
  "제육정식.png": "images/제육정식.png",
  "저장본.png": "images/저장본.png",
  "콜라.png": "images/콜라.png",
  "부대찌개.png": "images/부대찌개.png",
  "병원 접수증.jpg": "images/병원 접수증.jpg",
  "병원 영수증.jpg": "images/병원 영수증.jpg",
  "식당 영수증.jpg": "images/식당 영수증.jpg",
  "식당 주문서.jpg": "images/식당 주문서.jpg",
  "식당 키오스크 이미지.png": "images/식당 키오스크 이미지.png",
  "병원 키오스크 이미지 파일.png": "images/병원 키오스크 이미지 파일.png"
}